codexy-4.dist-info/METADATA
codexy-4.dist-info/WHEEL
codexy-4.dist-info/entry_points.txt
codexy-4.dist-info/licenses/LICENSE
codexy/__init__.py
codexy/__main__.py
codexy/approvals.py
codexy/cli/completion_scripts.py
codexy/cli/main.py
codexy/config.py
codexy/core/agent.py
codexy/exceptions.py
codexy/tools/__init__.py
codexy/tools/__pycache__/file_tools.cpython-312.pyc.1739407054800
codexy/tools/apply_diff_tool.py
codexy/tools/apply_patch_tool.py
codexy/tools/execute_command_tool.py
codexy/tools/file_tools.py
codexy/tui/__init__.py
codexy/tui/app.py
codexy/tui/widgets/__init__.py
codexy/tui/widgets/chat/__init__.py
codexy/tui/widgets/chat/command_review.py
codexy/tui/widgets/chat/header.py
codexy/tui/widgets/chat/history_view.py
codexy/tui/widgets/chat/input_area.py
codexy/tui/widgets/chat/message_display.py
codexy/tui/widgets/chat/thinking_indicator.py
codexy/tui/widgets/overlays/__init__.py
codexy/tui/widgets/overlays/approval_overlay.py
codexy/tui/widgets/overlays/help_overlay.py
codexy/tui/widgets/overlays/history_overlay.py
codexy/tui/widgets/overlays/model_overlay.py
codexy/utils/__init__.py
codexy/utils/filesystem.py
codexy/utils/model_info.py
codexy/utils/model_utils.py
codexy/utils/security_check.py
codexy/utils/storage.py
codexy/utils/token_utils.py
codexy/utils/update_checker.py
codexy-4.dist-info/RECORD
