Metadata-Version: 2.1
Name: codexy
Version: 4
Summary: A Python implementation of the Codex CLI tool.
Author-Email: AndersonBY <anderson@163.com>
Classifier: Programming Language :: Python :: 3
Classifier: License :: OSI Approved :: Apache Software License
Classifier: Operating System :: OS Independent
Classifier: Development Status :: 3 - Alpha
Classifier: Environment :: Console
Classifier: Intended Audience :: Developers
Classifier: Topic :: Software Development :: Code Generators
Project-URL: Bug Tracker, https://github.com/andersonby/codexy/issues
Project-URL: Homepage, https://github.com/andersonby/codexy
Requires-Python: >=3.10
Requires-Dist: click>=8.0
Requires-Dist: PyYAML>=6.0
Requires-Dist: openai>=1.0
Requires-Dist: rich>=13.0
Requires-Dist: detect-secrets>=1.5.0
Requires-Dist: textual
Requires-Dist: httpx>=0.28.1
Requires-Dist: packaging>=25.0
Requires-Dist: python-dotenv
